survte-0.3.0.data/scripts/survte
survte2/__init__.py
survte2/landxml_exporter.py
survte2/landxml_objects.py
survte2/landxml_parser.py
survte2/landxml_viewer.py
survte2/main.py
survte-0.3.0.dist-info/METADATA
survte-0.3.0.dist-info/WHEEL
survte-0.3.0.dist-info/top_level.txt
survte-0.3.0.dist-info/RECORD
