Metadata-Version: 2.1
Name: survte
Version: 0.3.0
Summary: A LandXML Viewer
Home-page: https://github.com/samanii2/survte
Author: Jakob Samani
Author-email: jakobsamani@gmail.com
Classifier: Programming Language :: Python :: 3
Classifier: License :: OSI Approved :: MIT License
Classifier: Operating System :: OS Independent
